blivet/__init__.py
blivet/actionlist.py
blivet/arch.py
blivet/blivet.py
blivet/callbacks.py
blivet/deviceaction.py
blivet/devicefactory.py
blivet/devicetree.py
blivet/errors.py
blivet/fcoe.py
blivet/flags.py
blivet/fstab.py
blivet/i18n.py
blivet/iscsi.py
blivet/mounts.py
blivet/nvme.py
blivet/partitioning.py
blivet/size.py
blivet/storage_log.py
blivet/threads.py
blivet/tsort.py
blivet/udev.py
blivet/util.py
blivet/zfcp.py
blivet/dbus/__init__.py
blivet/dbus/action.py
blivet/dbus/blivet.py
blivet/dbus/constants.py
blivet/dbus/device.py
blivet/dbus/format.py
blivet/dbus/manager.py
blivet/dbus/object.py
blivet/devicelibs/__init__.py
blivet/devicelibs/btrfs.py
blivet/devicelibs/crypto.py
blivet/devicelibs/disk.py
blivet/devicelibs/edd.py
blivet/devicelibs/gpt.py
blivet/devicelibs/lvm.py
blivet/devicelibs/mdraid.py
blivet/devicelibs/raid.py
blivet/devicelibs/stratis.py
blivet/devices/__init__.py
blivet/devices/btrfs.py
blivet/devices/cache.py
blivet/devices/container.py
blivet/devices/device.py
blivet/devices/disk.py
blivet/devices/dm.py
blivet/devices/file.py
blivet/devices/lib.py
blivet/devices/loop.py
blivet/devices/luks.py
blivet/devices/lvm.py
blivet/devices/md.py
blivet/devices/network.py
blivet/devices/nfs.py
blivet/devices/nodev.py
blivet/devices/optical.py
blivet/devices/partition.py
blivet/devices/raid.py
blivet/devices/storage.py
blivet/devices/stratis.py
blivet/events/__init__.py
blivet/events/changes.py
blivet/events/handler.py
blivet/events/manager.py
blivet/formats/__init__.py
blivet/formats/biosboot.py
blivet/formats/disklabel.py
blivet/formats/dmraid.py
blivet/formats/fs.py
blivet/formats/fslib.py
blivet/formats/luks.py
blivet/formats/lvmpv.py
blivet/formats/mdraid.py
blivet/formats/multipath.py
blivet/formats/prepboot.py
blivet/formats/stratis.py
blivet/formats/swap.py
blivet/populator/__init__.py
blivet/populator/populator.py
blivet/populator/helpers/__init__.py
blivet/populator/helpers/boot.py
blivet/populator/helpers/btrfs.py
blivet-3.13.0.dist-info/licenses/COPYING
blivet-3.13.0.dist-info/licenses/COPYING.LESSER
blivet-3.13.0.dist-info/METADATA
blivet-3.13.0.dist-info/WHEEL
blivet-3.13.0.dist-info/top_level.txt
blivet-3.13.0.dist-info/RECORD
