Metadata-Version: 2.4
Name: blivet
Version: 3.13.0
Summary: Python module for system storage configuration
Maintainer-email: Vojtech Trefny <vtrefny@redhat.com>
License:                     GNU GENERAL PUBLIC LICENSE
Project-URL: issues, https://github.com/storaged-project/blivet/issues
Project-URL: source, https://github.com/storaged-project/blivet
Project-URL: releasenotes, https://github.com/storaged-project/blivet/blob/main/release_notes.rst
Project-URL: documentation, https://storaged.org/blivet/
Classifier: Development Status :: 5 - Production/Stable
Classifier: Intended Audience :: Developers
Classifier: License :: OSI Approved :: GNU General Public License v2 or later (GPLv2+)
Classifier: Operating System :: POSIX :: Linux
Classifier: Topic :: System :: Operating System
License-File: COPYING
License-File: COPYING.LESSER
Requires-Dist: pyudev
Requires-Dist: dasbus
Dynamic: license-file
